<page>
<title>xisclessis</title>
<ns>0</ns>
<id>7091319</id>
<revision>
<id>51376507</id>
<timestamp>2019-01-29T04:07:41Z</timestamp>
<contributor>
<username>NadandoBot</username>
<id>394541</id>
</contributor>
<comment>Catalan inflected forms</comment>
<model>wikitext</model>
<format>text/x-wiki</format>
<text bytes="98" xml:space="preserve">==Catalan==
===Verb===
{{head|ca|verb form}}
# {{ca-verb form of|p=2|n=sg|t=impf|m=sub|xisclar}}</text>
<sha1>8m4tw5wufooc0kux7ol9dun4c6ft9eq</sha1>
</revision>
</page>
