<page>
<title>xristus</title>
<ns>0</ns>
<id>5941678</id>
<revision>
<id>52198943</id>
<parentid>50576412</parentid>
<timestamp>2019-04-01T11:02:28Z</timestamp>
<contributor>
<username>WingerBot</username>
<id>2024159</id>
</contributor>
<minor />
<comment>rename {{got-romanization of}} to {{romanization of|got}}</comment>
<model>wikitext</model>
<format>text/x-wiki</format>
<text bytes="98" xml:space="preserve">==Gothic==
===Romanization===
{{got-rom}}
# {{romanization of|got|ğ‡ğ‚ğŒ¹ğƒğ„ğŒ¿ğƒ}}</text>
<sha1>f087dp4fm7gswoabdefoklipbk700x5</sha1>
</revision>
</page>
