<page>
<title>xanthelasmoideorum</title>
<ns>0</ns>
<id>5405269</id>
<revision>
<id>66994990</id>
<parentid>56752752</parentid>
<timestamp>2022-05-15T09:45:42Z</timestamp>
<contributor>
<username>WingerBot</username>
<id>2024159</id>
</contributor>
<minor />
<comment>combine adjacent calls to {{inflection of|la|xanthelasmoīdeus}}; combine {{inflection of|la|xanthelasmoīdeus}} tag sets gen|m|p and gen|n|p into gen|m//n|p</comment>
<model>wikitext</model>
<format>text/x-wiki</format>
<text bytes="113" xml:space="preserve">==Latin==
===Noun===
{{la-noun-form|xanthelasmoīdeōrum}}
# {{inflection of|la|xanthelasmoīdeus||gen|m//n|p}}</text>
<sha1>tasdb5q3liizqiqapx5sk1r2y2u26in</sha1>
</revision>
</page>
