<page>
<title>xarrupats</title>
<ns>0</ns>
<id>5991062</id>
<revision>
<id>64460136</id>
<parentid>54734263</parentid>
<timestamp>2021-10-28T12:14:27Z</timestamp>
<contributor>
<username>SurjectionBot</username>
<id>3456416</id>
</contributor>
<comment>(bot) add rhyme syllable count obtained from Rhymes: pages</comment>
<model>wikitext</model>
<format>text/x-wiki</format>
<text bytes="166" xml:space="preserve">==Catalan==
===Pronunciation===
* {{ca-IPA}}
* {{rhymes|ca|ats|s=3}}
===Verb===
{{head|ca|past participle|g=m-p}}
# {{ca-verb form of|g=mpl|m=ptc|t=past|xarrupar}}</text>
<sha1>js3buo90871d73upijra7h6z6gdgasm</sha1>
</revision>
</page>
