<page>
<title>xenoparocho</title>
<ns>0</ns>
<id>4151599</id>
<revision>
<id>66995184</id>
<parentid>56274826</parentid>
<timestamp>2022-05-15T09:46:42Z</timestamp>
<contributor>
<username>WingerBot</username>
<id>2024159</id>
</contributor>
<minor />
<comment>combine adjacent calls to {{inflection of|la|xenoparochus}}; combine {{inflection of|la|xenoparochus}} tag sets dat|s and abl|s into dat//abl|s</comment>
<model>wikitext</model>
<format>text/x-wiki</format>
<text bytes="100" xml:space="preserve">==Latin==
===Noun===
{{la-noun-form|xenoparochō}}
# {{inflection of|la|xenoparochus||dat//abl|s}}</text>
<sha1>lvk6lyeyxpfedmdtz8cxunkulhk29g8</sha1>
</revision>
</page>
