<page>
<title>xeromammographically</title>
<ns>0</ns>
<id>5118012</id>
<revision>
<id>41916379</id>
<parentid>35931720</parentid>
<timestamp>2016-12-24T02:35:45Z</timestamp>
<contributor>
<username>Equinox</username>
<id>84390</id>
</contributor>
<minor />
<comment>ety</comment>
<model>wikitext</model>
<format>text/x-wiki</format>
<text bytes="127" xml:space="preserve">==English==
===Etymology===
{{suffix|en|xeromammographic|ally}}
===Adverb===
{{en-adv|-}}
# By means of [[xeromammography]].</text>
<sha1>rl4byodc7pwkas6n98vr52lx72zluzx</sha1>
</revision>
</page>
