<page>
<title>xerocollyriis</title>
<ns>0</ns>
<id>4151608</id>
<revision>
<id>66995214</id>
<parentid>56274863</parentid>
<timestamp>2022-05-15T09:46:53Z</timestamp>
<contributor>
<username>WingerBot</username>
<id>2024159</id>
</contributor>
<minor />
<comment>combine adjacent calls to {{inflection of|la|xērocollȳrium}}; combine {{inflection of|la|xērocollȳrium}} tag sets dat|p and abl|p into dat//abl|p</comment>
<model>wikitext</model>
<format>text/x-wiki</format>
<text bytes="107" xml:space="preserve">==Latin==
===Noun===
{{la-noun-form|xērocollȳriīs}}
# {{inflection of|la|xērocollȳrium||dat//abl|p}}</text>
<sha1>ie4248qz6elznmclegi7o1bzf6d8pce</sha1>
</revision>
</page>
