<page>
<title>xilografo</title>
<ns>0</ns>
<id>1625392</id>
<revision>
<id>65140437</id>
<parentid>51978934</parentid>
<timestamp>2022-01-02T10:47:28Z</timestamp>
<contributor>
<username>GianWiki</username>
<id>581633</id>
</contributor>
<comment>Added Pronunciation; expanded entry</comment>
<model>wikitext</model>
<format>text/x-wiki</format>
<text bytes="328" xml:space="preserve">==Italian==
===Alternative forms===
* {{alter|it|silografo}}
===Etymology===
{{confix|it|xilo|grafo}}
===Pronunciation===
{{it-pr|xilògrafo}}
===Noun===
{{it-noun|m|f=xilografa}}
# {{l|en|xylographer}}
====Related terms====
{{rel2|it|xilografia|xilografico}}
===References===
* {{R:it:Trec}}
{{C|it|Occupations|People}}</text>
<sha1>039ttybjecbdqrdmx0ofaoqirgu8h27</sha1>
</revision>
</page>
