<page>
<title>XSD</title>
<ns>0</ns>
<id>3940486</id>
<revision>
<id>59987695</id>
<parentid>54688221</parentid>
<timestamp>2020-08-07T08:05:17Z</timestamp>
<contributor>
<username>NadandoBot</username>
<id>394541</id>
</contributor>
<minor />
<comment>updating anagrams</comment>
<model>wikitext</model>
<format>text/x-wiki</format>
<text bytes="175" xml:space="preserve">==English==
===Proper noun===
{{en-proper noun}}
# {{lb|en|computing|Internet}} {{initialism of|en|{{w|XML Schema Definition}}}}
===Anagrams===
* {{anagrams|en|a=dsx|dx's}}</text>
<sha1>igmmem6el68do9vzx8iublq6oqc7vhe</sha1>
</revision>
</page>
