<page>
<title>yantabas</title>
<ns>0</ns>
<id>5055837</id>
<revision>
<id>68313434</id>
<parentid>44319600</parentid>
<timestamp>2022-07-18T13:17:25Z</timestamp>
<contributor>
<username>WingerBot</username>
<id>2024159</id>
</contributor>
<minor />
<comment>replace {{es-verb form of}} conjugation(s) for infinitive [[yantar]] with 'yantar'</comment>
<model>wikitext</model>
<format>text/x-wiki</format>
<text bytes="75" xml:space="preserve">==Spanish==
===Verb===
{{head|es|verb form}}
# {{es-verb form of|yantar}}</text>
<sha1>o5i8cg6jichv41d70jy9gyaq2zz8mwm</sha1>
</revision>
</page>
