<page>
<title>yarim</title>
<ns>0</ns>
<id>6476342</id>
<revision>
<id>48248963</id>
<timestamp>2017-12-11T05:58:54Z</timestamp>
<contributor>
<username>-sche</username>
<id>444485</id>
</contributor>
<comment>created based on Voorhoeve and fr.wikt</comment>
<model>wikitext</model>
<format>text/x-wiki</format>
<text bytes="114" xml:space="preserve">==Demta==
===Noun===
{{head|dmy|noun}}
# [[water]]
===Further reading===
* {{R:Voorhoeve Irian Jaya}}, page 112</text>
<sha1>63bzl2huxk6xwa8umbzdxl33dptu4cw</sha1>
</revision>
</page>
