<page>
<title>yarred</title>
<ns>0</ns>
<id>3065999</id>
<revision>
<id>50856705</id>
<parentid>47390204</parentid>
<timestamp>2018-11-27T05:29:12Z</timestamp>
<contributor>
<username>NadandoBot</username>
<id>394541</id>
</contributor>
<minor />
<comment>updating anagrams</comment>
<model>wikitext</model>
<format>text/x-wiki</format>
<text bytes="139" xml:space="preserve">==English==
===Verb===
{{head|en|verb form}}
# {{en-past of|yarr}}
===Anagrams===
* {{anagrams|en|a=aderry|Ardrey|Drayer|dreary|yarder}}</text>
<sha1>gh8p44jriree0e717a4sahedkroqb5z</sha1>
</revision>
</page>
