<page>
<title>yayamang</title>
<ns>0</ns>
<id>6358637</id>
<revision>
<id>47340054</id>
<timestamp>2017-08-25T05:48:54Z</timestamp>
<contributor>
<username>Mar vin kaiser</username>
<id>1141130</id>
</contributor>
<comment>Created page with &quot;==Tagalog==  ===Conjunction=== {{head|tl|conjunction}}  # [[since]]; [[inasmuch as]]  ====Synonyms==== * {{l|tl|yamang}}&quot;</comment>
<model>wikitext</model>
<format>text/x-wiki</format>
<text bytes="120" xml:space="preserve">==Tagalog==
===Conjunction===
{{head|tl|conjunction}}
# [[since]]; [[inasmuch as]]
====Synonyms====
* {{l|tl|yamang}}</text>
<sha1>djijolyzbsngn7tt9ueqgp0exw6yznw</sha1>
</revision>
</page>
