<page>
<title>ycovered</title>
<ns>0</ns>
<id>3046215</id>
<revision>
<id>58051783</id>
<parentid>54536248</parentid>
<timestamp>2019-11-24T06:18:05Z</timestamp>
<contributor>
<username>WingerBot</username>
<id>2024159</id>
</contributor>
<minor />
<comment>rename {{term-context}} to {{term-label}}</comment>
<model>wikitext</model>
<format>text/x-wiki</format>
<text bytes="156" xml:space="preserve">==English==
===Etymology===
{{prefix|en|y|covered}}
===Verb===
{{head|en|verb form}} {{term-label|en|obsolete}}
# {{past participle of|en|cover|nocat=1}}</text>
<sha1>gi86nopuloqku5p96pb1ymqcbnfvdjn</sha1>
</revision>
</page>
