<page>
<title>yhdistyn</title>
<ns>0</ns>
<id>854783</id>
<revision>
<id>32949592</id>
<parentid>27645863</parentid>
<timestamp>2015-06-09T20:46:38Z</timestamp>
<contributor>
<username>MewBot</username>
<id>345682</id>
</contributor>
<minor />
<comment>Removed unnecessary type= parameter</comment>
<model>wikitext</model>
<format>text/x-wiki</format>
<text bytes="131" xml:space="preserve">==Finnish==
===Verb===
{{head|fi|verb form}}
# {{fi-form of|pr=first-person|pl=singular|mood=indicative|tense=present|yhdistyä}}</text>
<sha1>lvu2o2ejfrzp5zpo0593jt2gybcl8hn</sha1>
</revision>
</page>
