<page>
<title>Yahudilere</title>
<ns>0</ns>
<id>6274336</id>
<revision>
<id>67914488</id>
<parentid>57616654</parentid>
<timestamp>2022-07-12T05:55:25Z</timestamp>
<contributor>
<username>WingerBot</username>
<id>2024159</id>
</contributor>
<minor />
<comment>Turkish: correct mistakes by [[User:Embryomystic]] (manually assisted)</comment>
<model>wikitext</model>
<format>text/x-wiki</format>
<text bytes="83" xml:space="preserve">==Turkish==
===Noun===
{{head|tr|noun form}}
# {{inflection of|tr|Yahudi||dat|p}}</text>
<sha1>rc40t6g0iamcsyzszzcfcbyrdguhdvi</sha1>
</revision>
</page>
