<page>
<title>yake</title>
<ns>0</ns>
<id>4716880</id>
<revision>
<id>62615016</id>
<parentid>46613811</parentid>
<timestamp>2021-05-27T12:12:26Z</timestamp>
<contributor>
<username>Samubert96</username>
<id>3098704</id>
</contributor>
<model>wikitext</model>
<format>text/x-wiki</format>
<text bytes="163" xml:space="preserve">{{also|Yake|yákē}}
==Swahili==
===Adjective===
{{head|sw|adjective form}}
# {{sw-adj form of|mi|ake}}
# {{sw-adj form of|ma|ake}}
# {{sw-adj form of|n|ake|sg}}</text>
<sha1>7csxsi0tb23levylab5zz4gdxttpofy</sha1>
</revision>
</page>
