<page>
<title>yakushimensis</title>
<ns>0</ns>
<id>3419667</id>
<revision>
<id>62019395</id>
<parentid>53913783</parentid>
<timestamp>2021-03-11T05:57:55Z</timestamp>
<contributor>
<username>J3133</username>
<id>3466327</id>
</contributor>
<model>wikitext</model>
<format>text/x-wiki</format>
<text bytes="181" xml:space="preserve">==Latin==
===Adjective===
{{la-adj|yakushimēnsis}}
# {{lb|la|relational|New Latin}} [[Yakushima]]
====Declension====
{{la-adecl|yakushimēnsis}}
{{cln|la|terms spelled with K}}</text>
<sha1>ns9ni34g087ftx62a0l0jnsrt09yp2x</sha1>
</revision>
</page>
