<page>
<title>yantaymaq</title>
<ns>0</ns>
<id>950650</id>
<revision>
<id>62143332</id>
<parentid>59831043</parentid>
<timestamp>2021-03-17T05:09:40Z</timestamp>
<contributor>
<username>DanielWhernchend</username>
<id>3677925</id>
</contributor>
<model>wikitext</model>
<format>text/x-wiki</format>
<text bytes="122" xml:space="preserve">==Crimean Tatar==
===Verb===
{{head|crh|verb}}
# to take a [[nap]], [[doze]]
====Conjugation====
{{crh-latin-conj|a|y}}</text>
<sha1>s8j37v9qcfygrw1h838b04ib1d5n5dr</sha1>
</revision>
</page>
