<page>
<title>yebs</title>
<ns>0</ns>
<id>2499904</id>
<revision>
<id>62405488</id>
<parentid>62405369</parentid>
<timestamp>2021-04-21T19:04:05Z</timestamp>
<contributor>
<username>Robbie SWE</username>
<id>24343</id>
</contributor>
<minor />
<comment>Reverted edits by [[Special:Contributions/150.176.145.17|150.176.145.17]]. If you think this rollback is in error, please leave a message on my talk page.</comment>
<model>wikitext</model>
<format>text/x-wiki</format>
<text bytes="77" xml:space="preserve">==Volapük==
===Noun===
{{head|vo|noun plural form}}
# {{plural of|vo|yeb}}</text>
<sha1>o4oqoatm4644v5qesarpmvlb13zt3ie</sha1>
</revision>
</page>
