<page>
<title>yeca</title>
<ns>0</ns>
<id>4213594</id>
<revision>
<id>65455797</id>
<parentid>55264300</parentid>
<timestamp>2022-01-26T09:33:17Z</timestamp>
<contributor>
<ip>186.158.132.93</ip>
</contributor>
<comment>/* Spanish */</comment>
<model>wikitext</model>
<format>text/x-wiki</format>
<text bytes="211" xml:space="preserve">==Eastern Huasteca Nahuatl==
===Adverb===
{{head|nhe|adverb}}
# [[then]]
----
==Spanish==
===Noun===
{{es-noun|f}}
# {{alternative spelling of|es|lleca}}
===Anagrams===
* {{anagrams|es|a=acey|yacé|yace}}</text>
<sha1>o7p9bwp2q7821hf4gxokvwsmthisxj9</sha1>
</revision>
</page>
