<page>
<title>yellowbacks</title>
<ns>0</ns>
<id>468054</id>
<revision>
<id>55353684</id>
<parentid>53093012</parentid>
<timestamp>2019-10-14T11:48:25Z</timestamp>
<contributor>
<username>WingerBot</username>
<id>2024159</id>
</contributor>
<minor />
<comment>move lang= to 1= in {{plural of}}</comment>
<model>wikitext</model>
<format>text/x-wiki</format>
<text bytes="76" xml:space="preserve">==English==
===Noun===
{{head|en|noun form}}
# {{plural of|en|yellowback}}</text>
<sha1>oyu9p1csfvv6is204vio1y1uxd7eic5</sha1>
</revision>
</page>
