<page>
<title>xenofobismos</title>
<ns>0</ns>
<id>6194354</id>
<revision>
<id>62879795</id>
<parentid>56159567</parentid>
<timestamp>2021-06-17T11:19:10Z</timestamp>
<contributor>
<username>WingerBot</username>
<id>2024159</id>
</contributor>
<minor />
<comment>noun plural form -&gt; noun form for Portuguese plurals</comment>
<model>wikitext</model>
<format>text/x-wiki</format>
<text bytes="84" xml:space="preserve">==Portuguese==
===Noun===
{{head|pt|noun form|g=m}}
# {{plural of|pt|xenofobismo}}</text>
<sha1>p2e067ox0eqmkskp5fg66nl9jvuya7y</sha1>
</revision>
</page>
