<page>
<title>xenotransplante</title>
<ns>0</ns>
<id>4589114</id>
<revision>
<id>69114389</id>
<parentid>29917753</parentid>
<timestamp>2022-09-04T16:53:43Z</timestamp>
<contributor>
<username>WingerBot</username>
<id>2024159</id>
</contributor>
<minor />
<comment>replace templated link to English term(s) in defns with raw link(s); misc cleanup esp. of 'Literally' and extraneous final periods (manually assisted)</comment>
<model>wikitext</model>
<format>text/x-wiki</format>
<text bytes="118" xml:space="preserve">==Portuguese==
===Noun===
{{pt-noun|m}}
# [[xenotransplantation]] {{gloss|transplantation into a different species}}</text>
<sha1>ckp6bes7t22o52key9pcf9qxumm2l6a</sha1>
</revision>
</page>
