<page>
<title>xerohalophytes</title>
<ns>0</ns>
<id>7356872</id>
<revision>
<id>54265863</id>
<timestamp>2019-09-22T07:28:36Z</timestamp>
<contributor>
<username>SemperBlotto</username>
<id>3336</id>
</contributor>
<comment>Creating forms of [[xerohalophyte]] ([[WT:ACCEL|Accelerated]])</comment>
<model>wikitext</model>
<format>text/x-wiki</format>
<text bytes="79" xml:space="preserve">==English==
===Noun===
{{head|en|noun form}}
# {{plural of|en|xerohalophyte}}</text>
<sha1>6r7d84cz9ucg2rg3ghekz5fsy21n29u</sha1>
</revision>
</page>
