<page>
<title>xhumana</title>
<ns>0</ns>
<id>6944477</id>
<revision>
<id>50533301</id>
<timestamp>2018-10-20T18:55:32Z</timestamp>
<contributor>
<username>AztecWarrior28</username>
<id>565513</id>
</contributor>
<comment>Created page with &quot;==Zulu==  ===Verb=== {{zu-verb}}  # to [[come]] together, to [[get]] in touch, to [[link]]  ====Inflection==== {{zu-infl-verb}}&quot;</comment>
<model>wikitext</model>
<format>text/x-wiki</format>
<text bytes="127" xml:space="preserve">==Zulu==
===Verb===
{{zu-verb}}
# to [[come]] together, to [[get]] in touch, to [[link]]
====Inflection====
{{zu-infl-verb}}</text>
<sha1>mirb4gydufvcuiryejecp5aeb5zpvrs</sha1>
</revision>
</page>
